pharmvar_tools/__init__.py
pharmvar_tools/api.py
pharmvar_tools/check.py
pharmvar_tools/compare.py
pharmvar_tools/config.py
pharmvar_tools/diff_relations.py
pharmvar_tools/lcsgraphs.py
pharmvar_tools/to_dot.py
pharmvar_tools/config/colors.yaml
pharmvar_tools/config/genes.yaml
pharmvar_tools-0.5.0.dist-info/LICENSE.md
pharmvar_tools-0.5.0.dist-info/METADATA
pharmvar_tools-0.5.0.dist-info/WHEEL
pharmvar_tools-0.5.0.dist-info/entry_points.txt
pharmvar_tools-0.5.0.dist-info/top_level.txt
pharmvar_tools-0.5.0.dist-info/RECORD
