Metadata-Version: 2.1
Name: pharmvar_tools
Version: 0.5.0
Summary: Python tools to work with Pharmvar data.
Author-email: Mark Santcroos <m.a.santcroos@lumc.nl>, "Jonathan K. Vis" <j.k.vis@lumc.nl>
Project-URL: Homepage, https://github.com/lumc-pgx/pharmvar-tools
Project-URL: Bug Tracker, https://github.com/lumc-pgx/pharmvar-tools/issues
Classifier: Programming Language :: Python :: 3
Classifier: License :: OSI Approved :: MIT License
Classifier: Operating System :: OS Independent
Requires-Python: >=3.7
License-File: LICENSE.md
Requires-Dist: mutalyzer-algebra
Requires-Dist: networkx
Requires-Dist: ratelimiter
Requires-Dist: requests
Requires-Dist: pyyaml
Provides-Extra: dev
Requires-Dist: build ; extra == 'dev'
Requires-Dist: twine ; extra == 'dev'
